ustache.py
ustache-0.1.6.dist-info/LICENSE
ustache-0.1.6.dist-info/METADATA
ustache-0.1.6.dist-info/WHEEL
ustache-0.1.6.dist-info/top_level.txt
ustache-0.1.6.dist-info/zip-safe
ustache-0.1.6.dist-info/RECORD
