Metadata-Version: 2.1
Name: ustache
Version: 0.1.6
Summary: ustache, Mustache for Python
Home-page: https://gitlab.com/ergoithz/ustache
Author: Felipe A Hernandez
Author-email: ergoithz@gmail.com
License: MIT
Keywords: template,mustache
Platform: any
Classifier: License :: OSI Approved :: MIT License
Classifier: Development Status :: 4 - Beta
Classifier: Operating System :: OS Independent
Classifier: Programming Language :: Python :: 3
Classifier: Programming Language :: Python :: 3.10
Classifier: Programming Language :: Python :: 3.11
Classifier: Programming Language :: Python :: 3.12
Classifier: Topic :: Software Development :: Libraries
Requires-Python: >=3.10.0
License-File: LICENSE
Requires-Dist: mstache==0.2.0
Provides-Extra: benchmark
Requires-Dist: chevron; extra == "benchmark"
Provides-Extra: codestyle
Requires-Dist: flake8; extra == "codestyle"
Requires-Dist: flake8-blind-except; extra == "codestyle"
Requires-Dist: flake8-bugbear; extra == "codestyle"
Requires-Dist: flake8-builtins; extra == "codestyle"
Requires-Dist: flake8-commas; extra == "codestyle"
Requires-Dist: flake8-docstrings; extra == "codestyle"
Requires-Dist: flake8-import-order; extra == "codestyle"
Requires-Dist: flake8-logging-format; extra == "codestyle"
Requires-Dist: flake8-rst-docstrings; extra == "codestyle"
Requires-Dist: flake8-simplify; extra == "codestyle"
Requires-Dist: mypy; extra == "codestyle"
Provides-Extra: coverage
Requires-Dist: coverage; extra == "coverage"
Provides-Extra: docs
Requires-Dist: recommonmark; extra == "docs"
Requires-Dist: sphinx; extra == "docs"
Requires-Dist: sphinx-autodoc-typehints; extra == "docs"
Provides-Extra: optional
Requires-Dist: xxhash>=1.2.0; extra == "optional"
Provides-Extra: release
Requires-Dist: wheel; extra == "release"
Requires-Dist: twine; extra == "release"
Provides-Extra: tests
Requires-Dist: coverage; extra == "tests"
Requires-Dist: xxhash; extra == "tests"
